civic_digital_twins/__init__.py
civic_digital_twins/dt_model/__init__.py
civic_digital_twins/dt_model/engine/__init__.py
civic_digital_twins/dt_model/engine/atomic/__init__.py
civic_digital_twins/dt_model/engine/compileflags/__init__.py
civic_digital_twins/dt_model/engine/frontend/__init__.py
civic_digital_twins/dt_model/engine/frontend/graph.py
civic_digital_twins/dt_model/engine/frontend/linearize.py
civic_digital_twins/dt_model/engine/frontend/pretty.py
civic_digital_twins/dt_model/engine/numpybackend/__init__.py
civic_digital_twins/dt_model/engine/numpybackend/debug.py
civic_digital_twins/dt_model/engine/numpybackend/executor.py
civic_digital_twins/dt_model/ensemble/__init__.py
civic_digital_twins/dt_model/internal/__init__.py
civic_digital_twins/dt_model/internal/sympyke/__init__.py
civic_digital_twins/dt_model/internal/sympyke/operators.py
civic_digital_twins/dt_model/internal/sympyke/piecewise.py
civic_digital_twins/dt_model/internal/sympyke/symbol.py
civic_digital_twins/dt_model/model/__init__.py
civic_digital_twins/dt_model/model/abstract_model.py
civic_digital_twins/dt_model/model/instantiated_model.py
civic_digital_twins/dt_model/reference_models/__init__.py
civic_digital_twins/dt_model/reference_models/molveno/__init__.py
civic_digital_twins/dt_model/reference_models/molveno/overtourism.py
civic_digital_twins/dt_model/reference_models/molveno/presence_stats.py
civic_digital_twins/dt_model/simulation/__init__.py
civic_digital_twins/dt_model/simulation/ensemble.py
civic_digital_twins/dt_model/simulation/evaluation.py
civic_digital_twins/dt_model/symbols/__init__.py
civic_digital_twins/dt_model/symbols/constraint.py
civic_digital_twins/dt_model/symbols/context_variable.py
civic_digital_twins/dt_model/symbols/index.py
civic_digital_twins/dt_model/symbols/presence_variable.py
civic_digital_twins-0.5.0.dist-info/METADATA
civic_digital_twins-0.5.0.dist-info/WHEEL
civic_digital_twins-0.5.0.dist-info/licenses/LICENSE
civic_digital_twins-0.5.0.dist-info/RECORD
