Metadata-Version: 2.4
Name: civic-digital-twins
Version: 0.5.0
Summary: Civic-Digital-Twins Modeling Framework
Project-URL: Homepage, https://github.com/fbk-most/dt-model
Author-email: Fondazione Bruno Kessler <most@fbk.eu>, Marco Pistore <pistore@fbk.eu>, Simone Basso <sibasso@fbk.eu>
License-Expression: Apache-2.0
License-File: LICENSE
Classifier: License :: OSI Approved :: Apache Software License
Classifier: Programming Language :: Python :: 3.11
Classifier: Programming Language :: Python :: 3.12
Classifier: Programming Language :: Python :: 3.13
Requires-Python: >=3.11.0
Requires-Dist: numpy>=2.2.0
Requires-Dist: pandas>=2.2.0
Requires-Dist: scipy>=1.15.0
